pyworksdoneutils/__init__.py
pyworksdoneutils/keycloak/__init__.py
pyworksdoneutils/keycloak/flask/__init__.py
pyworksdoneutils/keycloak/flask/_decorators.py
pyworksdoneutils/sqlalchemy/__init__.py
pyworksdoneutils/sqlalchemy/flask/__init__.py
pyworksdoneutils/sqlalchemy/flask/_decorators.py
py_worksdone_utils-1.1.6.dist-info/METADATA
py_worksdone_utils-1.1.6.dist-info/WHEEL
py_worksdone_utils-1.1.6.dist-info/top_level.txt
py_worksdone_utils-1.1.6.dist-info/RECORD
