Metadata-Version: 2.1
Name: py-worksdone-utils
Version: 1.1.6
Summary: Utilities with Keycloak
Author: KE
Author-email: 
Keywords: python,decorator,token,keycloak
Classifier: Development Status :: 1 - Planning
Classifier: Intended Audience :: Developers
Classifier: Programming Language :: Python :: 3.11
Classifier: Programming Language :: Python :: 3.12
Classifier: Operating System :: Unix
Classifier: Operating System :: MacOS
Requires-Dist: python-keycloak (==3.3.0)
